mprsync/__init__.py
mprsync/sync.py
mprsync-0.9.3.dist-info/licenses/LICENSE
mprsync-0.9.3.dist-info/METADATA
mprsync-0.9.3.dist-info/WHEEL
mprsync-0.9.3.dist-info/entry_points.txt
mprsync-0.9.3.dist-info/top_level.txt
mprsync-0.9.3.dist-info/RECORD
