Metadata-Version: 2.4
Name: mprsync
Version: 0.9.3
Summary: Run multiple rsync processes in parallel for local/remote data sync
Author-email: Sumedh Wale <sumwale@yahoo.com>
License:                                  Apache License
Project-URL: Homepage, https://github.com/sumwale/mprsync
Project-URL: Issues, https://github.com/sumwale/mprsync/issues
Keywords: Multiprocess rsync,Parallel rsync,rsync
Classifier: Development Status :: 4 - Beta
Classifier: Intended Audience :: End Users/Desktop
Classifier: License :: OSI Approved :: Apache Software License
Classifier: Operating System :: OS Independent
Classifier: Programming Language :: Python :: 3
Classifier: Programming Language :: Python :: 3.10
Classifier: Programming Language :: Python :: 3.11
Classifier: Programming Language :: Python :: 3.12
Classifier: Programming Language :: Python :: 3.13
Requires-Python: >=3.10
License-File: LICENSE
Dynamic: license-file
